ossobuco/__init__.py
ossobuco/analyzer.py
ossobuco/displayer.py
ossobuco/gap.py
ossobuco/reader.py
ossobuco/simulation.py
ossobuco/utils.py
ossobuco-0.0.2.dist-info/LICENSE.md
ossobuco-0.0.2.dist-info/METADATA
ossobuco-0.0.2.dist-info/WHEEL
ossobuco-0.0.2.dist-info/top_level.txt
ossobuco-0.0.2.dist-info/RECORD
