Metadata-Version: 2.2
Name: ossobuco
Version: 0.0.2
Summary: surface growth simulations for structural build-up investigations
Author-email: Luca Michel <micheluc@ethz.ch>, Flavio Lorez <florez@ethz.ch>, Antoine Sanner <asanner@ethz.ch>, David Kammer <dkammer@ethz.ch>
License: GNU Lesser General Public License v3 (LGPLv3)
License-File: LICENSE.md
Requires-Dist: numpy
Requires-Dist: bamboost
Requires-Dist: matplotlib
Requires-Dist: scipy
